changes.txt
setup.py
alchemist/__init__.py
alchemist.audit.egg-info/PKG-INFO
alchemist.audit.egg-info/SOURCES.txt
alchemist.audit.egg-info/dependency_links.txt
alchemist.audit.egg-info/namespace_packages.txt
alchemist.audit.egg-info/not-zip-safe
alchemist.audit.egg-info/requires.txt
alchemist.audit.egg-info/top_level.txt
alchemist/audit/__init__.py
alchemist/audit/audit.py
alchemist/audit/browser.py
alchemist/audit/changes.pt
alchemist/audit/configure.zcml
alchemist/audit/i18n.py
alchemist/audit/interfaces.py
alchemist/audit/readme.txt
alchemist/audit/recorder.py
alchemist/audit/schema.py