Metadata-Version: 1.0
Name: alchemist.audit
Version: 0.3.2
Summary: Alchemist Auditing Components ( Event Subscribers, Change Recorders, UI ) for Relational Applications
Home-page: http://code.google.com/p/zope-alchemist
Author: Kapil Thangavelu
Author-email: kapil.foss@gmail.com
License: ZPL
Keywords: zope3 audit
Platform: UNKNOWN
Classifier: Programming Language :: Python
Classifier: Framework :: Zope3
